[
    {
        "id": "0",
        "text": "一键约车",
        "badge":"",
        "icon":"cluster-o",
        "to":"/h5_pactcar"
    },
    {
        "id": "1",
        "text": "未派车",
        "badge":"",
        "icon":"records",
        "to":"/h5_wp"
    },
    {
        "id": "2",
        "text": "已派车",
        "badge":"",
        "icon":"description",
        "to":"/h5_yp"
    },
    {
        "id": "3",
        "text": "等待车",
        "badge":"",
        "icon":"description",
        "to":"/h5_dd"
    },
    {
        "id": "4",
        "text": "车辆管理",
        "badge":"",
        "icon":"setting-o",
        "to":"/h5_setcar"
    },
    {
        "id": "5",
        "text": "车辆录入",
        "badge":"",
        "icon":"edit",
        "to":"/h5_carlr"
    },
    {
        "id": "6",
        "text": "司机订单列表",
        "badge":"",
        "icon":"records",
        "to":"/h5_carztdamin"
    }
]